{"current":{"sections":{"collection-list":{"type":"collection-list","blocks":{"collection-list-0":{"type":"collection","settings":{"collection":""}},"collection-list-1":{"type":"collection","settings":{"collection":""}},"collection-list-2":{"type":"collection","settings":{"collection":""}}},"block_order":["collection-list-0","collection-list-1","collection-list-2"],"settings":{"title":"Collection list"}},"featured-collection":{"type":"featured-collection","settings":{"title":"Featured collection","collection":"frontpage"}},"featured-product":{"type":"featured-product","settings":{"product":"","show_share_buttons":false}},"header":{"type":"header","settings":{"logo":"shopify:\/\/shop_images\/logo-transparent.png","logo_text":"Brand","logo_width":80,"logo_width_mobile":60,"header_height":90,"menu_font_size":16,"menu_font_family":"'Segoe UI', Arial, sans-serif","header_padding_top":20,"header_padding_bottom":20,"menu_padding":12,"icon_padding":8,"header_layout":"flex","header_container_width":"1200","logo_position":"left","main_menu":"main-menu","menu_position":"middle","show_search":true,"search_inline":true,"show_account":true,"show_cart":true,"icon_search_v2":"fa-solid fa-magnifying-glass","icon_account_v2":"fa-solid fa-user","icon_logout_v2":"fa-solid fa-arrow-right-from-bracket","icon_cart_v2":"fa-solid fa-cart-shopping","icon_color":"#2563eb","show_announcement":true,"announcement_text":"Welcome to our store!","header_bg_color":"#111827","header_text_color":"#000000","menu_text_color":"#2563eb"}},"footer":{"type":"footer","settings":{"column_count":"4","logo":"shopify:\/\/shop_images\/logo-transparent.png","logo_width":60,"address":"122 Abul Hasnat Road Dhaka","phone":"01914226125","mobile":"01914226125","email":"nnglobal2004@gmail.com","menu_title":"Quick links","footer_menu":"footer","news_title":"Subscribe","social_title":"Follow us","facebook":"","twitter":"","instagram":"","bg_top":"#111827","bg_bottom":"#0f172a","text_color":"#e5e7eb","text_size":14,"text_font":"'Segoe UI', Arial, sans-serif","heading_color":"#ffffff","heading_size":16,"col_w_1":1,"col_w_2":1,"col_w_3":1,"col_w_4":1,"show_payments":true}}},"content_for_index":["collection-list","featured-collection","featured-product"]},"presets":{"Default":{"sections":{"collection-list":{"type":"collection-list","blocks":{"collection-list-0":{"type":"collection","settings":{}},"collection-list-1":{"type":"collection","settings":{}},"collection-list-2":{"type":"collection","settings":{}}},"block_order":["collection-list-0","collection-list-1","collection-list-2"],"settings":{}},"featured-collection":{"type":"featured-collection","settings":{"collection":"frontpage"}},"featured-product":{"type":"featured-product","settings":{}}},"content_for_index":["collection-list","featured-collection","featured-product"]}}}